odoo/addons/website_js_below_the_fold_payment/README.rst
odoo/addons/website_js_below_the_fold_payment/__init__.py
odoo/addons/website_js_below_the_fold_payment/__manifest__.py
odoo/addons/website_js_below_the_fold_payment/i18n/fr.po
odoo/addons/website_js_below_the_fold_payment/i18n/it.po
odoo/addons/website_js_below_the_fold_payment/i18n/pt_BR.po
odoo/addons/website_js_below_the_fold_payment/i18n/website_js_below_the_fold_payment.pot
odoo/addons/website_js_below_the_fold_payment/readme/CONTRIBUTORS.rst
odoo/addons/website_js_below_the_fold_payment/readme/DESCRIPTION.rst
odoo/addons/website_js_below_the_fold_payment/readme/ROADMAP.rst
odoo/addons/website_js_below_the_fold_payment/static/description/icon.png
odoo/addons/website_js_below_the_fold_payment/static/description/index.html
odoo/addons/website_js_below_the_fold_payment/templates/templates.xml
odoo12_addon_website_js_below_the_fold_payment-12.0.1.0.0.99.dev8.dist-info/METADATA
odoo12_addon_website_js_below_the_fold_payment-12.0.1.0.0.99.dev8.dist-info/WHEEL
odoo12_addon_website_js_below_the_fold_payment-12.0.1.0.0.99.dev8.dist-info/top_level.txt
odoo12_addon_website_js_below_the_fold_payment-12.0.1.0.0.99.dev8.dist-info/RECORD
